UpdateSystem-0.0.7.data/scripts/us
UpdateSystem-0.0.7.dist-info/DESCRIPTION.rst
UpdateSystem-0.0.7.dist-info/METADATA
UpdateSystem-0.0.7.dist-info/RECORD
UpdateSystem-0.0.7.dist-info/WHEEL
UpdateSystem-0.0.7.dist-info/metadata.json
UpdateSystem-0.0.7.dist-info/top_level.txt
UpdateSystem-0.0.7.dist-info/zip-safe
updatesystem/__init__.py
updatesystem/api.py
updatesystem/app.py
updatesystem/check.py
updatesystem/cli.py
updatesystem/configparser.py
updatesystem/log.py
updatesystem/orchestra.py
updatesystem/result.py
updatesystem/task.py
