Metadata-Version: 2.0
Name: UpdateSystem
Version: 0.0.7
Summary: update system 
Home-page: UNKNOWN
Author: shalk
Author-email: shalk@aliyun.com
License: MIT
Platform: UNKNOWN
